teamcity/__init__.py
teamcity/teamcity.py
teamcity/teamcity_const.py
python_teamcity-0.3.0.dist-info/AUTHORS
python_teamcity-0.3.0.dist-info/LICENSE
python_teamcity-0.3.0.dist-info/METADATA
python_teamcity-0.3.0.dist-info/WHEEL
python_teamcity-0.3.0.dist-info/pbr.json
python_teamcity-0.3.0.dist-info/top_level.txt
python_teamcity-0.3.0.dist-info/RECORD
